benchmarks/__init__.py
benchmarks/benchmarks.py
torch_bessel-0.0.8.dist-info/METADATA
torch_bessel-0.0.8.dist-info/RECORD
torch_bessel-0.0.8.dist-info/top_level.txt
torch_bessel-0.0.8.dist-info/WHEEL
torch_bessel-0.0.8.dist-info/licenses/LICENSE
torch_bessel/__init__.py
torch_bessel/ops.py
torch_bessel/_C.cpython-311-x86_64-linux-gnu.so
