Metadata-Version: 2.4
Name: torch_bessel
Version: 0.0.8
Summary: PyTorch extension package for Bessel functions with arbitrary real order and complex inputs
Home-page: https://github.com/hchau630/torch-bessel
Author: Ho Yin Chau
Requires-Python: >= 3.9
License-File: LICENSE
Requires-Dist: torch
Dynamic: author
Dynamic: description
Dynamic: description-content-type
Dynamic: home-page
Dynamic: license-file
Dynamic: requires-dist
Dynamic: requires-python
Dynamic: summary
